uproot_browser/__init__.py
uproot_browser/__main__.py
uproot_browser/_version.py
uproot_browser/_version.pyi
uproot_browser/exceptions.py
uproot_browser/plot.py
uproot_browser/plot_mpl.py
uproot_browser/py.typed
uproot_browser/tree.py
uproot_browser/tui/README.md
uproot_browser/tui/__init__.py
uproot_browser/tui/browser.css
uproot_browser/tui/browser.py
uproot_browser/tui/error.py
uproot_browser/tui/header.py
uproot_browser/tui/help.py
uproot_browser/tui/left_panel.py
uproot_browser/tui/logo.py
uproot_browser/tui/messages.py
uproot_browser/tui/plot.py
uproot_browser/tui/tools.py
uproot_browser/tui/viewer.py
uproot_browser-0.8.4.dist-info/METADATA
uproot_browser-0.8.4.dist-info/WHEEL
uproot_browser-0.8.4.dist-info/entry_points.txt
uproot_browser-0.8.4.dist-info/licenses/LICENSE
uproot_browser-0.8.4.dist-info/RECORD
