Metadata-Version: 2.4
Name: uproot_browser
Version: 0.8.4
Summary: Tools to inspect ROOT files with uproot
Project-URL: homepage, https://github.com/scikit-hep/uproot-browser
Project-URL: repository, https://github.com/scikit-hep/uproot-browser
Author-email: Henry Schreiner <henryfs@princeton.edu>
Maintainer-email: The Scikit-HEP admins <scikit-hep-admins@googlegroups.com>
License-File: LICENSE
Classifier: Development Status :: 4 - Beta
Classifier: Intended Audience :: Developers
Classifier: Intended Audience :: Science/Research
Classifier: License :: OSI Approved :: BSD License
Classifier: Operating System :: OS Independent
Classifier: Programming Language :: Python
Classifier: Programming Language :: Python :: 3
Classifier: Programming Language :: Python :: 3.9
Classifier: Programming Language :: Python :: 3.10
Classifier: Programming Language :: Python :: 3.11
Classifier: Programming Language :: Python :: 3.12
Classifier: Programming Language :: Python :: 3.13
Classifier: Programming Language :: Python :: 3.14
Classifier: Topic :: Scientific/Engineering
Classifier: Typing :: Typed
Requires-Python: >=3.9
Requires-Dist: awkward>=2
Requires-Dist: click-default-group>=1.2
Requires-Dist: click>=8
Requires-Dist: hist>=2.4
Requires-Dist: lz4>=2
Requires-Dist: numpy>=1.18
Requires-Dist: plotext>=5.2.8
Requires-Dist: rich>=13.3.3
Requires-Dist: textual>=0.86.0
Requires-Dist: uproot>=5.6.1
Provides-Extra: iterm
Requires-Dist: itermplot==0.5; extra == 'iterm'
Requires-Dist: matplotlib; extra == 'iterm'
Requires-Dist: mplhep; extra == 'iterm'
Provides-Extra: testdata
Requires-Dist: scikit-hep-testdata>=0.5.0; extra == 'testdata'
